Workbook

Sheet Presupuesto
A2: 💰 TRACKER DE PRESUPUESTO PERSONAL
A4: SALARIO QUINCENAL | C4: 670 | D4: ← Ingresa tu salario aquí
A6: # | B6: Descripción del Gasto | C6: Monto (B/.) | D6: ¿Pagado? | E6: Monto Pagado
A7: 1 | B7: PrestYa | C7: 80 | D7: ✅ Sí | E7: =IF(D7="✅ Sí",C7,0) -> 80
A8: 2 | B8: Electricidad | C8: 0 | D8: ❌ No | E8: =IF(D8="✅ Sí",C8,0) -> 0
A9: 3 | B9: Celu | C9: 70 | D9: ✅ Sí | E9: =IF(D9="✅ Sí",C9,0) -> 70
A10: 4 | B10: Internet / Teléfono | C10: 25 | D10: ✅ Sí | E10: =IF(D10="✅ Sí",C10,0) -> 25
A11: 5 | B11: Supermercado | C11: 0 | D11: ❌ No | E11: =IF(D11="✅ Sí",C11,0) -> 0
A12: 6 | B12: Transporte / Gasolina | C12: 60 | D12: ✅ Sí | E12: =IF(D12="✅ Sí",C12,0) -> 60
A13: 7 | B13: Ocio | C13: 60 | D13: ✅ Sí | E13: =IF(D13="✅ Sí",C13,0) -> 60
A14: 8 | B14: Tarjeta de crédito | C14: 159 | D14: ✅ Sí | E14: =IF(D14="✅ Sí",C14,0) -> 159
A15: 9 | B15: Matricula | C15: 41 | D15: ✅ Sí | E15: =IF(D15="✅ Sí",C15,0) -> 41
A16: 10 | B16: Zapatos | C16: 60 | D16: ✅ Sí | E16: =IF(D16="✅ Sí",C16,0) -> 60
A17: 11 | B17: Pantalón negro | C17: 20 | D17: ❌ No | E17: =IF(D17="✅ Sí",C17,0) -> 0
A18: 12 | B18: Kevin | C18: 33 | D18: ✅ Sí | E18: =IF(D18="✅ Sí",C18,0) -> 33
... A21: 15 | B21: Gym | C21: 15 | D21: ✅ Sí | E21: =IF(D21="✅ Sí",C21,0) -> 15
A23: TOTAL DE GASTOS | C23: =SUM(C7:C21) -> 680 | D23: =TEXT(COUNTA(A7:A21),"0")&" gastos registrados" -> 15 gastos registrados
A24: TOTAL PAGADO | C24: =SUM(E7:E21) -> 660 | D24: =COUNTIF(D7:D21,"✅ Sí")&" de 15 pagados" -> 12 de 15 pagados
A25: BALANCE RESTANTE | C25: =C4-SUM(E7:E21) -> 10 | D25: Salario − Gastos pagados

Sheet 30 Abril
A2: 💰 TRACKER DE PRESUPUESTO PERSONAL
A4: SALARIO QUINCENAL | C4: 395 | D4: ← Ingresa tu salario aquí
A6: # | B6: Descripción del Gasto | C6: Monto (B/.) | D6: ¿Pagado? | E6: Monto Pagado | F6: Monto debt
A7: 1 | B7: PrestYa | C7: 80 | D7: ✅ Sí | E7: =IF(D7="✅ Sí",C7,0) -> 80 | F7: 344
A8: 2 | B8: Novey | C8: 19.59 | D8: ✅ Sí | E8: =IF(D8="✅ Sí",C8,0) -> 19.59 | F8: 0
A9: 3 | B9: Celu | C9: 0 | D9: ❌ No | E9: =IF(D9="✅ Sí",C9,0) -> 0 | F9: 1330
A10: 4 | B10: Internet / Teléfono | C10: 25 | D10: ✅ Sí | E10: =IF(D10="✅ Sí",C10,0) -> 25 | F10: 0
A11: 5 | B11: Supermercado | C11: 0 | D11: ❌ No | E11: =IF(D11="✅ Sí",C11,0) -> 0 | F11: 0
A12: 6 | B12: Transporte / Gasolina | C12: 60 | D12: ✅ Sí | E12: =IF(D12="✅ Sí",C12,0) -> 60 | F12: 0
A13: 7 | B13: Ocio | C13: 60 | D13: ✅ Sí | E13: =IF(D13="✅ Sí",C13,0) -> 60 | F13: 0
A14: 8 | B14: Tarjeta de crédito | C14: 109 | D14: ✅ Sí | E14: =IF(D14="✅ Sí",C14,0) -> 109 | F14: 1565
A15: 9 | B15: Cesar | C15: 21.4 | D15: ✅ Sí | E15: =IF(D15="✅ Sí",C15,0) -> 21.4 | F15: 0
A16: 10 | C16: 0 | D16: ❌ No | E16: =IF(D16="✅ Sí",C16,0) -> 0 | F16: 0
A17: 11 | C17: 0 | D17: ❌ No | E17: =IF(D17="✅ Sí",C17,0) -> 0 | F17: 0
A18: 12 | C18: 0 | D18: ❌ No | E18: =IF(D18="✅ Sí",C18,0) -> 0 | F18: 0
A19: 13 | C19: 0 | D19: ❌ No | E19: =IF(D19="✅ Sí",C19,0) -> 0 | F19: 0
A20: 14 | C20: 0 | D20: ❌ No | E20: =IF(D20="✅ Sí",C20,0) -> 0 | F20: 0
A21: 15 | C21: 0 | D21: ❌ No | E21: =IF(D21="✅ Sí",C21,0) -> 0 | F21: 0
A23: TOTAL DE GASTOS | C23: =SUM(C7:C21) -> 374.99 | D23: =TEXT(COUNTA(A7:A21),"0")&" gastos registrados" -> 15 gastos registrados
A24: TOTAL PAGADO | C24: =SUM(E7:E21) -> 374.99 | D24: =COUNTIF(D7:D21,"✅ Sí")&" de 15 pagados" -> 7 de 15 pagados
A25: BALANCE RESTANTE | C25: =C4-SUM(E7:E21) -> 20.01 | D25: Salario − Gastos pagados

Sheet 15deMayo
A2: 💰 TRACKER DE PRESUPUESTO PERSONAL
A4: SALARIO QUINCENAL | C4: 505 | D4: ← Ingresa tu salario aquí
A6: # | B6: Descripción del Gasto | C6: Monto (B/.) | D6: ¿Pagado? | E6: Monto Pagado | F6: Monto debt
A7: 1 | B7: PrestYa | C7: 75 | D7: ✅ Sí | E7: =IF(D7="✅ Sí",C7,0) -> 75 | F7: 273
A8: 2 | B8: Tarjeta de crédito | C8: 130 | D8: ✅ Sí | E8: =IF(D8="✅ Sí",C8,0) -> 130 | F8: =1665-(C8+C13)+30+C14 -> 1580 | H8: =1680-F8 -> 100
A9: 3 | B9: Celu | C9: 70 | D9: ✅ Sí | E9: =IF(D9="✅ Sí",C9,0) -> 70 | F9: 1260
A10: 4 | B10: Internet / Teléfono | C10: 25 | D10: ✅ Sí | E10: =IF(D10="✅ Sí",C10,0) -> 25 | F10: 0
A11: 5 | B11: Ocio | C11: 60 | D11: ✅ Sí | E11: =IF(D11="✅ Sí",C11,0) -> 60 | F11: 0
A12: 6 | B12: Transporte / Gasolina | C12: 60 | D12: ✅ Sí | E12: =IF(D12="✅ Sí",C12,0) -> 60 | F12: 0
A13: 7 | B13: Bag | C13: 5 | D13: ✅ Sí | E13: =IF(D13="✅ Sí",C13,0) -> 5 | F13: 0
A14: 8 | B14: Samuel | C14: 20 | D14: ✅ Sí | E14: =IF(D14="✅ Sí",C14,0) -> 20 | F14: 0
A15: 9 | C15: 0 | D15: ❌ No | E15: =IF(D15="✅ Sí",C15,0) -> 0 | F15: 0
A16: 10 | C16: 0 | D16: ❌ No | E16: =IF(D16="✅ Sí",C16,0) -> 0 | F16: 0
A17: 11 | C17: 0 | D17: ❌ No | E17: =IF(D17="✅ Sí",C17,0) -> 0 | F17: 0
A18: 12 | C18: 0 | D18: ❌ No | E18: =IF(D18="✅ Sí",C18,0) -> 0 | F18: 0
A19: 13 | C19: 0 | D19: ❌ No | E19: =IF(D19="✅ Sí",C19,0) -> 0 | F19: 0
A20: 14 | C20: 0 | D20: ❌ No | E20: =IF(D20="✅ Sí",C20,0) -> 0 | F20: 0
A21: 15 | C21: 0 | D21: ❌ No | E21: =IF(D21="✅ Sí",C21,0) -> 0 | F21: 0
A23: TOTAL DE GASTOS | C23: =SUM(C7:C21) -> 445 | D23: =TEXT(COUNTA(A7:A21),"0")&" gastos registrados" -> 15 gastos registrados
A24: TOTAL PAGADO | C24: =SUM(E7:E21) -> 445 | D24: =COUNTIF(D7:D21,"✅ Sí")&" de 15 pagados" -> 8 de 15 pagados
A25: BALANCE RESTANTE | C25: =C4-SUM(E7:E21) -> 60 | D25: Salario − Gastos pagados

Sheet 30 de Mayo
A2: 💰 TRACKER DE PRESUPUESTO PERSONAL
A4: SALARIO QUINCENAL | C4: 505 | D4: ← Ingresa tu salario aquí
A6: # | B6: Descripción del Gasto | C6: Monto (B/.) | D6: ¿Pagado? | E6: Monto Pagado | F6: Monto debt
A7: 1 | B7: PrestYa | C7: 95 | D7: ✅ Sí | E7: =IF(D7="✅ Sí",C7,0) -> 95 | F7: 174 | H7: =1680-F8 -> 315
A8: 2 | B8: Tarjeta de crédito | C8: 215 | D8: ✅ Sí | E8: =IF(D8="✅ Sí",C8,0) -> 215 | F8: ='15deMayo'!F8 - C8 -> 1365
A9: 3 | B9: Celu | C9: 0 | D9: ✅ Sí | E9: =IF(D9="✅ Sí",C9,0) -> 0 | F9: 1225
A10: 4 | B10: Internet / Teléfono | C10: 25 | D10: ✅ Sí | E10: =IF(D10="✅ Sí",C10,0) -> 25 | F10: 0
A11: 5 | B11: Ocio | C11: 80 | D11: ✅ Sí | E11: =IF(D11="✅ Sí",C11,0) -> 80 | F11: 0
A12: 6 | B12: Transporte / Gasolina | C12: 60 | D12: ✅ Sí | E12: =IF(D12="✅ Sí",C12,0) -> 60 | F12: 0
A13: 7 | B13: David | C13: 5 | D13: ✅ Sí | E13: =IF(D13="✅ Sí",C13,0) -> 5 | F13: 0
A14: 8 | C14: 0 | D14: ❌ No | E14: =IF(D14="✅ Sí",C14,0) -> 0 | F14: 0
A15: 9 | C15: 0 | D15: ❌ No | E15: =IF(D15="✅ Sí",C15,0) -> 0 | F15: 0
A16: 10 | C16: 0 | D16: ❌ No | E16: =IF(D16="✅ Sí",C16,0) -> 0 | F16: 0
A17: 11 | C17: 0 | D17: ❌ No | E17: =IF(D17="✅ Sí",C17,0) -> 0 | F17: 0
A18: 12 | C18: 0 | D18: ❌ No | E18: =IF(D18="✅ Sí",C18,0) -> 0 | F18: 0
A19: 13 | C19: 0 | D19: ❌ No | E19: =IF(D19="✅ Sí",C19,0) -> 0 | F19: 0
A20: 14 | C20: 0 | D20: ❌ No | E20: =IF(D20="✅ Sí",C20,0) -> 0 | F20: 0
A21: 15 | C21: 0 | D21: ❌ No | E21: =IF(D21="✅ Sí",C21,0) -> 0 | F21: 0
A23: TOTAL DE GASTOS | C23: =SUM(C7:C21) -> 480 | D23: =TEXT(COUNTA(A7:A21),"0")&" gastos registrados" -> 15 gastos registrados
A24: TOTAL PAGADO | C24: =SUM(E7:E21) -> 480 | D24: =COUNTIF(D7:D21,"✅ Sí")&" de 15 pagados" -> 7 de 15 pagados
A25: BALANCE RESTANTE | C25: =C4-SUM(E7:E21) -> 25 | D25: Salario − Gastos pagados

Sheet 15 de Junio
A2: 💰 TRACKER DE PRESUPUESTO PERSONAL
A4: SALARIO QUINCENAL | C4: 505 | D4: ← Ingresa tu salario aquí
A6: # | B6: Descripción del Gasto | C6: Monto (B/.) | D6: ¿Pagado? | E6: Monto Pagado | F6: Monto debt
A7: 1 | B7: PrestYa | C7: 70 | D7: ✅ Sí | E7: =IF(D7="✅ Sí",C7,0) -> 70 | F7: 89
A8: 2 | B8: Tarjeta de crédito | C8: 10 | D8: ❌ No | E8: =IF(D8="✅ Sí",C8,0) -> 0 | F8: ='30 de Mayo'!F8 *1.022 - C8 -> 1385.03 | H8: =1680-F8 -> 294.97
A9: 3 | B9: Celu | C9: 70 | D9: ✅ Sí | E9: =IF(D9="✅ Sí",C9,0) -> 70 | F9: 1190
A10: 4 | B10: Internet / Teléfono | C10: 20 | D10: ✅ Sí | E10: =IF(D10="✅ Sí",C10,0) -> 20 | F10: 0
A11: 5 | B11: Ocio | C11: 60 | D11: ✅ Sí | E11: =IF(D11="✅ Sí",C11,0) -> 60 | F11: 0
A12: 6 | B12: Transporte / Gasolina | C12: 50 | D12: ✅ Sí | E12: =IF(D12="✅ Sí",C12,0) -> 50 | F12: 0
A13: 7 | B13: Dad | C13: 30 | D13: ❌ No | E13: =IF(D13="✅ Sí",C13,0) -> 0 | F13: 0
A14: 8 | C14: 0 | D14: ❌ No | E14: =IF(D14="✅ Sí",C14,0) -> 0 | F14: 0
A15: 9 | C15: 0 | D15: ❌ No | E15: =IF(D15="✅ Sí",C15,0) -> 0 | F15: 0
A16: 10 | C16: 0 | D16: ❌ No | E16: =IF(D16="✅ Sí",C16,0) -> 0 | F16: 0
A17: 11 | C17: 0 | D17: ❌ No | E17: =IF(D17="✅ Sí",C17,0) -> 0 | F17: 0
A18: 12 | C18: 0 | D18: ❌ No | E18: =IF(D18="✅ Sí",C18,0) -> 0 | F18: 0
A19: 13 | C19: 0 | D19: ❌ No | E19: =IF(D19="✅ Sí",C19,0) -> 0 | F19: 0
A20: 14 | C20: 0 | D20: ❌ No | E20: =IF(D20="✅ Sí",C20,0) -> 0 | F20: 0
A21: 15 | C21: 0 | D21: ❌ No | E21: =IF(D21="✅ Sí",C21,0) -> 0 | F21: 0
A23: TOTAL DE GASTOS | C23: =SUM(C7:C21) -> 310 | D23: =TEXT(COUNTA(A7:A21),"0")&" gastos registrados" -> 15 gastos registrados
A24: TOTAL PAGADO | C24: =SUM(E7:E21) -> 270 | D24: =COUNTIF(D7:D21,"✅ Sí")&" de 15 pagados" -> 5 de 15 pagados
A25: BALANCE RESTANTE | C25: =C4-SUM(E7:E21) -> 235 | D25: Salario − Gastos pagados

Sheet 30 de Junio
A2: 💰 TRACKER DE PRESUPUESTO PERSONAL
A4: SALARIO QUINCENAL | C4: 505 | D4: ← Ingresa tu salario aquí
A6: # | B6: Descripción del Gasto | C6: Monto (B/.) | D6: ¿Pagado? | E6: Monto Pagado | F6: Monto debt
A7: 1 | B7: PrestYa | C7: 70 | D7: ✅ Sí | E7: =IF(D7="✅ Sí",C7,0) -> 70 | F7: 0
A8: 2 | B8: Tarjeta de crédito | C8: 90 | D8: ❌ No | E8: =IF(D8="✅ Sí",C8,0) -> 0 | F8: ='15 de Junio'!F8 - C8 -> 1295.03 | H8: =1680-F8 -> 384.97
A9: 3 | B9: Celu | C9: 0 | D9: ✅ Sí | E9: =IF(D9="✅ Sí",C9,0) -> 0 | F9: 1155
A10: 4 | B10: Internet / Teléfono | C10: 25 | D10: ✅ Sí | E10: =IF(D10="✅ Sí",C10,0) -> 25 | F10: 0
A11: 5 | B11: Ocio | C11: 80 | D11: ✅ Sí | E11: =IF(D11="✅ Sí",C11,0) -> 80 | F11: 0
A12: 6 | B12: Transporte / Gasolina | C12: 60 | D12: ✅ Sí | E12: =IF(D12="✅ Sí",C12,0) -> 60 | F12: 0
A13: 7 | C13: 0 | D13: ❌ No | E13: =IF(D13="✅ Sí",C13,0) -> 0 | F13: 0
A14: 8 | C14: 0 | D14: ❌ No | E14: =IF(D14="✅ Sí",C14,0) -> 0 | F14: 0
A15: 9 | C15: 0 | D15: ❌ No | E15: =IF(D15="✅ Sí",C15,0) -> 0 | F15: 0
A16: 10 | C16: 0 | D16: ❌ No | E16: =IF(D16="✅ Sí",C16,0) -> 0 | F16: 0
A17: 11 | C17: 0 | D17: ❌ No | E17: =IF(D17="✅ Sí",C17,0) -> 0 | F17: 0
A18: 12 | C18: 0 | D18: ❌ No | E18: =IF(D18="✅ Sí",C18,0) -> 0 | F18: 0
A19: 13 | C19: 0 | D19: ❌ No | E19: =IF(D19="✅ Sí",C19,0) -> 0 | F19: 0
A20: 14 | C20: 0 | D20: ❌ No | E20: =IF(D20="✅ Sí",C20,0) -> 0 | F20: 0
A21: 15 | C21: 0 | D21: ❌ No | E21: =IF(D21="✅ Sí",C21,0) -> 0 | F21: 0
A23: TOTAL DE GASTOS | C23: =SUM(C7:C21) -> 325 | D23: =TEXT(COUNTA(A7:A21),"0")&" gastos registrados" -> 15 gastos registrados
A24: TOTAL PAGADO | C24: =SUM(E7:E21) -> 235 | D24: =COUNTIF(D7:D21,"✅ Sí")&" de 15 pagados" -> 5 de 15 pagados
A25: BALANCE RESTANTE | C25: =C4-SUM(E7:E21) -> 270 | D25: Salario − Gastos pagados

Sheet 15 de Julio
A2: 💰 TRACKER DE PRESUPUESTO PERSONAL
A4: SALARIO QUINCENAL | C4: 505 | D4: ← Ingresa tu salario aquí
A6: # | B6: Descripción del Gasto | C6: Monto (B/.) | D6: ¿Pagado? | E6: Monto Pagado | F6: Monto debt
A7: 6 | B7: Tarjeta de crédito | C7: 125.76 | D7: ✅ Sí | E7: =IF(D7="✅ Sí",C7,0) -> 125.76 | F7: ='30 de Junio'!F8 *1.022 -C7 -> 1197.7607 | H7: =1680-F7 -> 482.23934
A8: 2 | B8: Celu | C8: 70 | D8: ✅ Sí | E8: =IF(D8="✅ Sí",C8,0) -> 70 | F8: 1120
A9: 3 | B9: Internet / Teléfono | C9: 25 | D9: ✅ Sí | E9: =IF(D9="✅ Sí",C9,0) -> 25 | F9: 0
A10: 4 | B10: Ocio | C10: 80 | D10: ✅ Sí | E10: =IF(D10="✅ Sí",C10,0) -> 80 | F10: 0
A11: 5 | B11: Transporte / Gasolina | C11: 60 | D11: ✅ Sí | E11: =IF(D11="✅ Sí",C11,0) -> 60 | F11: 0
A12: 6 | B12: Help ppl | C12: 0 | D12: ❌ No | E12: =IF(D12="✅ Sí",C12,0) -> 0 | F12: 0
A13: 7 | B13: PYa | C13: 42 | D13: ✅ Sí | E13: =IF(D13="✅ Sí",C13,0) -> 42 | F13: 0
A14: 8 | B14: Bday | C14: 60 | D14: ❌ No | E14: =IF(D14="✅ Sí",C14,0) -> 0 | F14: 0
A15: 9 | C15: 0 | D15: ❌ No | E15: =IF(D15="✅ Sí",C15,0) -> 0 | F15: 0
A16: 10 | C16: 0 | D16: ❌ No | E16: =IF(D16="✅ Sí",C16,0) -> 0 | F16: 0
A17: 11 | C17: 0 | D17: ❌ No | E17: =IF(D17="✅ Sí",C17,0) -> 0 | F17: 0
A18: 12 | C18: 0 | D18: ❌ No | E18: =IF(D18="✅ Sí",C18,0) -> 0 | F18: 0
A19: 13 | C19: 0 | D19: ❌ No | E19: =IF(D19="✅ Sí",C19,0) -> 0 | F19: 0
A20: 14 | C20: 0 | D20: ❌ No | E20: =IF(D20="✅ Sí",C20,0) -> 0 | F20: 0
A21: 15 | C21: 0 | D21: ❌ No | E21: =IF(D21="✅ Sí",C21,0) -> 0 | F21: 0
A23: TOTAL DE GASTOS | C23: =SUM(C7:C21) -> 462.76 | D23: =TEXT(COUNTA(A7:A21),"0")&" gastos registrados" -> 15 gastos registrados
A24: TOTAL PAGADO | C24: =SUM(E7:E21) -> 402.76 | D24: =COUNTIF(D7:D21,"✅ Sí")&" de 15 pagados" -> 6 de 15 pagados
A25: BALANCE RESTANTE | C25: =C4-SUM(E7:E21) -> 102.24 | D25: Salario − Gastos pagados

Sheet 30 de Julio
A2: 💰 TRACKER DE PRESUPUESTO PERSONAL
A4: SALARIO QUINCENAL | C4: 505 | D4: ← Ingresa tu salario aquí
A6: # | B6: Descripción del Gasto | C6: Monto (B/.) | D6: ¿Pagado? | E6: Monto Pagado | F6: Monto debt
A7: 6 | B7: Tarjeta de crédito | C7: 0 | D7: ❌ No | E7: =IF(D7="✅ Sí",C7,0) -> 0 | F7: ='15 de Julio'!F7 - C7 -> 1197.7607 | H7: =1680-F7 -> 482.23934
A8: 2 | B8: Celu | C8: 0 | D8: ✅ Sí | E8: =IF(D8="✅ Sí",C8,0) -> 0 | F8: 1085
A9: 3 | B9: Internet / Teléfono | C9: 25 | D9: ✅ Sí | E9: =IF(D9="✅ Sí",C9,0) -> 25 | F9: 0
A10: 4 | B10: Ocio | C10: 80 | D10: ✅ Sí | E10: =IF(D10="✅ Sí",C10,0) -> 80 | F10: 0
A11: 5 | B11: Transporte / Gasolina | C11: 60 | D11: ✅ Sí | E11: =IF(D11="✅ Sí",C11,0) -> 60 | F11: 0
A12: 6 | C12: 0 | D12: ❌ No | E12: =IF(D12="✅ Sí",C12,0) -> 0 | F12: 0
A13: 7 | C13: 0 | D13: ❌ No | E13: =IF(D13="✅ Sí",C13,0) -> 0 | F13: 0
A14: 8 | C14: 0 | D14: ❌ No | E14: =IF(D14="✅ Sí",C14,0) -> 0 | F14: 0
A15: 9 | C15: 0 | D15: ❌ No | E15: =IF(D15="✅ Sí",C15,0) -> 0 | F15: 0
A16: 10 | C16: 0 | D16: ❌ No | E16: =IF(D16="✅ Sí",C16,0) -> 0 | F16: 0
A17: 11 | C17: 0 | D17: ❌ No | E17: =IF(D17="✅ Sí",C17,0) -> 0 | F17: 0
A18: 12 | C18: 0 | D18: ❌ No | E18: =IF(D18="✅ Sí",C18,0) -> 0 | F18: 0
A19: 13 | C19: 0 | D19: ❌ No | E19: =IF(D19="✅ Sí",C19,0) -> 0 | F19: 0
A20: 14 | C20: 0 | D20: ❌ No | E20: =IF(D20="✅ Sí",C20,0) -> 0 | F20: 0
A21: 15 | C21: 0 | D21: ❌ No | E21: =IF(D21="✅ Sí",C21,0) -> 0 | F21: 0
A23: TOTAL DE GASTOS | C23: =SUM(C7:C21) -> 165 | D23: =TEXT(COUNTA(A7:A21),"0")&" gastos registrados" -> 15 gastos registrados
A24: TOTAL PAGADO | C24: =SUM(E7:E21) -> 165 | D24: =COUNTIF(D7:D21,"✅ Sí")&" de 15 pagados" -> 4 de 15 pagados
A25: BALANCE RESTANTE | C25: =C4-SUM(E7:E21) -> 340 | D25: Salario − Gastos pagados

Sheet 15 de Agosto
A2: 💰 TRACKER DE PRESUPUESTO PERSONAL
A4: SALARIO QUINCENAL | C4: =505+270 -> 775 | D4: ← Ingresa tu salario aquí
A6: # | B6: Descripción del Gasto | C6: Monto (B/.) | D6: ¿Pagado? | E6: Monto Pagado | F6: Monto debt
A7: 6 | B7: Tarjeta de crédito | C7: 115 | D7: ❌ No | E7: =IF(D7="✅ Sí",C7,0) -> 0 | F7: ='30 de Julio'!F7 *1.02 - C7 -> 1106.7159 | H7: REDUCIR A 1000$ | I7: =1680-F7 -> 573.28413
A8: 2 | B8: Celu | C8: 70 | D8: ✅ Sí | E8: =IF(D8="✅ Sí",C8,0) -> 70 | F8: 1050
A9: 3 | B9: Internet / Teléfono | C9: 25 | D9: ✅ Sí | E9: =IF(D9="✅ Sí",C9,0) -> 25 | F9: 0
A10: 4 | B10: Ocio | C10: 80 | D10: ✅ Sí | E10: =IF(D10="✅ Sí",C10,0) -> 80 | F10: 0
A11: 5 | B11: Transporte / Gasolina | C11: 60 | D11: ✅ Sí | E11: =IF(D11="✅ Sí",C11,0) -> 60 | F11: 0
A12: 6 | B12: Aniversario | C12: 250 | D12: ✅ Sí | E12: =IF(D12="✅ Sí",C12,0) -> 250 | F12: 0
A13: 7 | B13: susu | C13: 100 | D13: ✅ Sí | E13: =IF(D13="✅ Sí",C13,0) -> 100 | F13: 0
A14: 8 | B14: Jimmy | C14: 75 | D14: ✅ Sí | E14: =IF(D14="✅ Sí",C14,0) -> 75 | F14: 0
A15: 9 | C15: 0 | D15: ❌ No | E15: =IF(D15="✅ Sí",C15,0) -> 0 | F15: 0
A16: 10 | C16: 0 | D16: ❌ No | E16: =IF(D16="✅ Sí",C16,0) -> 0 | F16: 0
A17: 11 | C17: 0 | D17: ❌ No | E17: =IF(D17="✅ Sí",C17,0) -> 0 | F17: 0
A18: 12 | C18: 0 | D18: ❌ No | E18: =IF(D18="✅ Sí",C18,0) -> 0 | F18: 0
A19: 13 | C19: 0 | D19: ❌ No | E19: =IF(D19="✅ Sí",C19,0) -> 0 | F19: 0
A20: 14 | C20: 0 | D20: ❌ No | E20: =IF(D20="✅ Sí",C20,0) -> 0 | F20: 0
A21: 15 | C21: 0 | D21: ❌ No | E21: =IF(D21="✅ Sí",C21,0) -> 0 | F21: 0
A23: TOTAL DE GASTOS | C23: =SUM(C7:C21) -> 775 | D23: =TEXT(COUNTA(A7:A21),"0")&" gastos registrados" -> 15 gastos registrados
A24: TOTAL PAGADO | C24: =SUM(E7:E21) -> 660 | D24: =COUNTIF(D7:D21,"✅ Sí")&" de 15 pagados" -> 7 de 15 pagados
A25: BALANCE RESTANTE | C25: =C4-SUM(E7:E21) -> 115 | D25: Salario − Gastos pagados

Sheet 30deAgosto
A2: 💰 TRACKER DE PRESUPUESTO PERSONAL
A4: SALARIO QUINCENAL | C4: 505 | D4: ← Ingresa tu salario aquí
A6: # | B6: Descripción del Gasto | C6: Monto (B/.) | D6: ¿Pagado? | E6: Monto Pagado | F6: Monto debt
A7: 6 | B7: Tarjeta de crédito | C7: 240 | D7: ❌ No | E7: =IF(D7="✅ Sí",C7,0) -> 0 | F7: ='15 de Agosto'!F7 - C7 -> 866.71587 | H7: REDUCIR A 1000$
A8: 2 | B8: Celu | C8: 0 | D8: ✅ Sí | E8: =IF(D8="✅ Sí",C8,0) -> 0 | F8: 1050
A9: 3 | B9: Internet / Teléfono | C9: 25 | D9: ✅ Sí | E9: =IF(D9="✅ Sí",C9,0) -> 25 | F9: 0
A10: 4 | B10: Ocio | C10: 80 | D10: ✅ Sí | E10: =IF(D10="✅ Sí",C10,0) -> 80 | F10: 0
A11: 5 | B11: Transporte / Gasolina | C11: 60 | D11: ✅ Sí | E11: =IF(D11="✅ Sí",C11,0) -> 60 | F11: 0
A12: 6 | B12: susu | C12: 100 | D12: ✅ Sí | E12: =IF(D12="✅ Sí",C12,0) -> 100 | F12: 0
A13: 7 | C13: 0 | D13: ❌ No | E13: =IF(D13="✅ Sí",C13,0) -> 0 | F13: 0
A14: 8 | C14: 0 | D14: ❌ No | E14: =IF(D14="✅ Sí",C14,0) -> 0 | F14: 0
A15: 9 | C15: 0 | D15: ❌ No | E15: =IF(D15="✅ Sí",C15,0) -> 0 | F15: 0
A16: 10 | C16: 0 | D16: ❌ No | E16: =IF(D16="✅ Sí",C16,0) -> 0 | F16: 0
A17: 11 | C17: 0 | D17: ❌ No | E17: =IF(D17="✅ Sí",C17,0) -> 0 | F17: 0
A18: 12 | C18: 0 | D18: ❌ No | E18: =IF(D18="✅ Sí",C18,0) -> 0 | F18: 0
A19: 13 | C19: 0 | D19: ❌ No | E19: =IF(D19="✅ Sí",C19,0) -> 0 | F19: 0
A20: 14 | C20: 0 | D20: ❌ No | E20: =IF(D20="✅ Sí",C20,0) -> 0 | F20: 0
A21: 15 | C21: 0 | D21: ❌ No | E21: =IF(D21="✅ Sí",C21,0) -> 0 | F21: 0
A23: TOTAL DE GASTOS | C23: =SUM(C7:C21) -> 505 | D23: =TEXT(COUNTA(A7:A21),"0")&" gastos registrados" -> 15 gastos registrados
A24: TOTAL PAGADO | C24: =SUM(E7:E21) -> 265 | D24: =COUNTIF(D7:D21,"✅ Sí")&" de 15 pagados" -> 5 de 15 pagados
A25: BALANCE RESTANTE | C25: =C4-SUM(E7:E21) -> 240 | D25: Salario − Gastos pagados

Sheet 15deSep
A2: 💰 TRACKER DE PRESUPUESTO PERSONAL
A4: SALARIO QUINCENAL | C4: 505 | D4: ← Ingresa tu salario aquí
A6: # | B6: Descripción del Gasto | C6: Monto (B/.) | D6: ¿Pagado? | E6: Monto Pagado | F6: Monto debt
A7: 6 | B7: Tarjeta de crédito | C7: 170 | D7: ❌ No | E7: =IF(D7="✅ Sí",C7,0) -> 0 | F7: ='30deAgosto'!F7 *1.02 - C7 -> 714.05019 | H7: REDUCIR A 1000$
A8: 2 | B8: Celu | C8: 70 | D8: ✅ Sí | E8: =IF(D8="✅ Sí",C8,0) -> 70 | F8: 1050
A9: 3 | B9: Internet / Teléfono | C9: 25 | D9: ✅ Sí | E9: =IF(D9="✅ Sí",C9,0) -> 25 | F9: 0
A10: 4 | B10: Ocio | C10: 80 | D10: ✅ Sí | E10: =IF(D10="✅ Sí",C10,0) -> 80 | F10: 0
A11: 5 | B11: Transporte / Gasolina | C11: 60 | D11: ✅ Sí | E11: =IF(D11="✅ Sí",C11,0) -> 60 | F11: 0
A12: 6 | B12: susu | C12: 100 | D12: ✅ Sí | E12: =IF(D12="✅ Sí",C12,0) -> 100 | F12: 0
A13: 7 | C13: 0 | D13: ❌ No | E13: =IF(D13="✅ Sí",C13,0) -> 0 | F13: 0
A14: 8 | C14: 0 | D14: ❌ No | E14: =IF(D14="✅ Sí",C14,0) -> 0 | F14: 0
A15: 9 | C15: 0 | D15: ❌ No | E15: =IF(D15="✅ Sí",C15,0) -> 0 | F15: 0
A16: 10 | C16: 0 | D16: ❌ No | E16: =IF(D16="✅ Sí",C16,0) -> 0 | F16: 0
A17: 11 | C17: 0 | D17: ❌ No | E17: =IF(D17="✅ Sí",C17,0) -> 0 | F17: 0
A18: 12 | C18: 0 | D18: ❌ No | E18: =IF(D18="✅ Sí",C18,0) -> 0 | F18: 0
A19: 13 | C19: 0 | D19: ❌ No | E19: =IF(D19="✅ Sí",C19,0) -> 0 | F19: 0
A20: 14 | C20: 0 | D20: ❌ No | E20: =IF(D20="✅ Sí",C20,0) -> 0 | F20: 0
A21: 15 | C21: 0 | D21: ❌ No | E21: =IF(D21="✅ Sí",C21,0) -> 0 | F21: 0
A23: TOTAL DE GASTOS | C23: =SUM(C7:C21) -> 505 | D23: =TEXT(COUNTA(A7:A21),"0")&" gastos registrados" -> 15 gastos registrados
A24: TOTAL PAGADO | C24: =SUM(E7:E21) -> 335 | D24: =COUNTIF(D7:D21,"✅ Sí")&" de 15 pagados" -> 5 de 15 pagados
A25: BALANCE RESTANTE | C25: =C4-SUM(E7:E21) -> 170 | D25: Salario − Gastos pagados
